home/runner/.synapseConfig
synapseclient/.synapseConfig
synapseclient/__init__.py
synapseclient/__main__.py
synapseclient/activity.py
synapseclient/annotations.py
synapseclient/client.py
synapseclient/entity.py
synapseclient/evaluation.py
synapseclient/synapsePythonClient
synapseclient/table.py
synapseclient/team.py
synapseclient/wiki.py
synapseclient/api/__init__.py
synapseclient/api/agent_services.py
synapseclient/api/annotations.py
synapseclient/api/api_client.py
synapseclient/api/configuration_services.py
synapseclient/api/curation_services.py
synapseclient/api/entity_bundle_services_v2.py
synapseclient/api/entity_factory.py
synapseclient/api/entity_services.py
synapseclient/api/file_services.py
synapseclient/api/json_schema_services.py
synapseclient/api/table_services.py
synapseclient/api/team_services.py
synapseclient/api/user_services.py
synapseclient/core/__init__.py
synapseclient/core/async_utils.py
synapseclient/core/cache.py
synapseclient/core/config.py
synapseclient/core/cumulative_transfer_progress.py
synapseclient/core/dozer.py
synapseclient/core/exceptions.py
synapseclient/core/lock.py
synapseclient/core/logging_setup.py
synapseclient/core/otel_config.py
synapseclient/core/pool_provider.py
synapseclient/core/remote_file_storage_wrappers.py
synapseclient/core/retry.py
synapseclient/core/sts_transfer.py
synapseclient/core/transfer_bar.py
synapseclient/core/utils.py
synapseclient/core/version_check.py
synapseclient/core/constants/__init__.py
synapseclient/core/constants/concrete_types.py
synapseclient/core/constants/config_file_constants.py
synapseclient/core/constants/limits.py
synapseclient/core/constants/method_flags.py
synapseclient/core/credentials/__init__.py
synapseclient/core/credentials/cred_data.py
synapseclient/core/credentials/credential_provider.py
synapseclient/core/download/__init__.py
synapseclient/core/download/download_async.py
synapseclient/core/download/download_functions.py
synapseclient/core/models/__init__.py
synapseclient-4.10.0.dist-info/METADATA
synapseclient-4.10.0.dist-info/WHEEL
synapseclient-4.10.0.dist-info/entry_points.txt
synapseclient-4.10.0.dist-info/top_level.txt
synapseclient-4.10.0.dist-info/RECORD
