Metadata-Version: 2.4
Name: synapseclient
Version: 4.10.0
Summary: A client for Synapse, a collaborative, open-source research platform that allows teams to share data, track analyses, and collaborate.
Home-page: https://www.synapse.org
Author: The Synapse Engineering Team
Author-email: platform@sagebase.org
License: Apache-2.0
Project-URL: Source, https://github.com/Sage-Bionetworks/synapsePythonClient
Project-URL: Tracker, https://github.com/Sage-Bionetworks/synapsePythonClient/issues
Project-URL: Documentation, https://python-docs.synapse.org
Project-URL: Changelog, https://python-docs.synapse.org/en/stable/news/
Platform: any
Classifier: Development Status :: 5 - Production/Stable
Classifier: Programming Language :: Python
Classifier: Programming Language :: Python :: 3.9
Classifier: Programming Language :: Python :: 3.10
Classifier: Programming Language :: Python :: 3.11
Classifier: Programming Language :: Python :: 3.12
Classifier: Programming Language :: Python :: 3.13
Classifier: Operating System :: MacOS
Classifier: Operating System :: Microsoft :: Windows
Classifier: Operating System :: Unix
Classifier: Operating System :: POSIX :: Linux
Classifier: Intended Audience :: Developers
Classifier: Intended Audience :: Science/Research
Classifier: License :: OSI Approved :: Apache Software License
Classifier: Topic :: Software Development :: Libraries
Classifier: Topic :: Scientific/Engineering
Classifier: Topic :: Scientific/Engineering :: Bio-Informatics
Requires-Python: <3.14,>=3.9
Requires-Dist: requests<3.0,>=2.22.0
Requires-Dist: urllib3<2,>=1.26.18
Requires-Dist: deprecated<2.0,>=1.2.4
Requires-Dist: opentelemetry-api>=1.21.0
Requires-Dist: opentelemetry-sdk>=1.21.0
Requires-Dist: opentelemetry-exporter-otlp-proto-http>=1.21.0
Requires-Dist: opentelemetry-instrumentation-httpx>=0.48b0
Requires-Dist: opentelemetry-instrumentation-requests>=0.48b0
Requires-Dist: opentelemetry-instrumentation-threading>=0.48b0
Requires-Dist: opentelemetry-instrumentation-urllib>=0.48b0
Requires-Dist: nest-asyncio~=1.6.0
Requires-Dist: asyncio-atexit~=1.0.1
Requires-Dist: httpx>=0.27.0
Requires-Dist: httpcore>=1.0.9
Requires-Dist: tqdm<5.0,>=4.66.2
Requires-Dist: async-lru~=2.0.4
Requires-Dist: psutil~=5.9.8
Provides-Extra: dev
Requires-Dist: pytest~=8.2.0; extra == "dev"
Requires-Dist: pytest-mock<4.0,>=3.0; extra == "dev"
Requires-Dist: pytest-socket~=0.6.0; extra == "dev"
Requires-Dist: pytest-asyncio<2.0,>=1.2.0; extra == "dev"
Requires-Dist: flake8<4.0,>=3.7.0; extra == "dev"
Requires-Dist: pytest-xdist[psutil]<3.0.0,>=2.2; extra == "dev"
Requires-Dist: pytest-rerunfailures~=12.0; extra == "dev"
Requires-Dist: func-timeout~=4.3; extra == "dev"
Requires-Dist: pytest-cov~=4.1.0; extra == "dev"
Requires-Dist: black; extra == "dev"
Requires-Dist: pre-commit; extra == "dev"
Requires-Dist: pandas<3.0,>=1.5; extra == "dev"
Provides-Extra: tests
Requires-Dist: pytest~=8.2.0; extra == "tests"
Requires-Dist: pytest-mock<4.0,>=3.0; extra == "tests"
Requires-Dist: pytest-socket~=0.6.0; extra == "tests"
Requires-Dist: pytest-asyncio<2.0,>=1.2.0; extra == "tests"
Requires-Dist: flake8<4.0,>=3.7.0; extra == "tests"
Requires-Dist: pytest-xdist[psutil]<3.0.0,>=2.2; extra == "tests"
Requires-Dist: pytest-rerunfailures~=12.0; extra == "tests"
Requires-Dist: func-timeout~=4.3; extra == "tests"
Requires-Dist: pytest-cov~=4.1.0; extra == "tests"
Requires-Dist: pandas<3.0,>=1.5; extra == "tests"
Provides-Extra: pandas
Requires-Dist: pandas<3.0,>=1.5; extra == "pandas"
Provides-Extra: pysftp
Requires-Dist: pysftp<0.3,>=0.2.8; extra == "pysftp"
Requires-Dist: paramiko<4.0.0; extra == "pysftp"
Provides-Extra: boto3
Requires-Dist: boto3<2.0,>=1.7.0; extra == "boto3"
Provides-Extra: docs
Requires-Dist: mkdocs>=1.5.3; extra == "docs"
Requires-Dist: mkdocs-material>=9.4.14; extra == "docs"
Requires-Dist: mkdocstrings>=0.24.0; extra == "docs"
Requires-Dist: mkdocstrings-python>=1.8.0; extra == "docs"
Requires-Dist: termynal>=0.11.1; extra == "docs"
Requires-Dist: mkdocs-open-in-new-tab~=1.0.3; extra == "docs"
Requires-Dist: markdown-include~=0.8.1; extra == "docs"
